tdbalarm/__init__.py
tdbalarm/dao.py
tdbalarm/model.py
tdbalarm/tdbalarm.py
tdbalarm/cli/__init__.py
tdbalarm/cli/schema.py
tdbalarm/cli/tdbalarm.py
tessdb/__init__.py
tessdb/_version.py
tessdb/constants.py
tessdb/dbase.py
tessdb/filter.py
tessdb/http.py
tessdb/logger.py
tessdb/mqtt.py
tessdb/server.py
tessdb/stats.py
tessdb_server-5.0.9.data/scripts/tessdb_flush
tessdb_server-5.0.9.data/scripts/tessdb_hello
tessdb_server-5.0.9.data/scripts/tessdb_pause
tessdb_server-5.0.9.data/scripts/tessdb_reload
tessdb_server-5.0.9.data/scripts/tessdb_resume
tessdb_server-5.0.9.data/scripts/tessdb_stats
tessdb_server-5.0.9.dist-info/licenses/LICENSE
tessdb_server-5.0.9.dist-info/METADATA
tessdb_server-5.0.9.dist-info/WHEEL
tessdb_server-5.0.9.dist-info/entry_points.txt
tessdb_server-5.0.9.dist-info/top_level.txt
tessdb_server-5.0.9.dist-info/RECORD
